agno/__init__.py
agno/debug.py
agno/exceptions.py
agno/filters.py
agno/media.py
agno/py.typed
agno/table.py
agno/agent/__init__.py
agno/agent/agent.py
agno/agent/remote.py
agno/api/__init__.py
agno/api/agent.py
agno/api/api.py
agno/api/evals.py
agno/api/os.py
agno/api/routes.py
agno/api/settings.py
agno/api/team.py
agno/api/workflow.py
agno/api/schemas/__init__.py
agno/api/schemas/agent.py
agno/api/schemas/evals.py
agno/api/schemas/os.py
agno/api/schemas/response.py
agno/api/schemas/team.py
agno/api/schemas/utils.py
agno/api/schemas/workflows.py
agno/client/__init__.py
agno/client/os.py
agno/cloud/aws/base.py
agno/cloud/aws/s3/__init__.py
agno/cloud/aws/s3/api_client.py
agno/cloud/aws/s3/bucket.py
agno/cloud/aws/s3/object.py
agno/compression/__init__.py
agno/compression/manager.py
agno/culture/__init__.py
agno/culture/manager.py
agno/db/__init__.py
agno/db/base.py
agno/db/utils.py
agno/db/async_postgres/__init__.py
agno/db/dynamo/__init__.py
agno/db/dynamo/dynamo.py
agno/db/dynamo/schemas.py
agno/db/dynamo/utils.py
agno/db/firestore/__init__.py
agno/db/firestore/firestore.py
agno/db/firestore/schemas.py
agno/db/firestore/utils.py
agno/db/gcs_json/__init__.py
agno/db/gcs_json/gcs_json_db.py
agno/db/gcs_json/utils.py
agno/db/in_memory/__init__.py
agno/db/in_memory/in_memory_db.py
agno/db/in_memory/utils.py
agno/db/json/__init__.py
agno/db/json/json_db.py
agno/db/json/utils.py
agno/db/migrations/__init__.py
agno/db/migrations/manager.py
agno/db/migrations/v1_to_v2.py
agno/db/migrations/versions/__init__.py
agno/db/migrations/versions/v2_3_0.py
agno/db/mongo/__init__.py
agno/db/mongo/async_mongo.py
agno/db/mongo/mongo.py
agno/db/mongo/schemas.py
agno/db/mongo/utils.py
agno/db/mysql/__init__.py
agno/db/mysql/async_mysql.py
agno/db/mysql/mysql.py
agno/db/mysql/schemas.py
agno/db/mysql/utils.py
agno/db/postgres/__init__.py
agno/db/postgres/async_postgres.py
agno/db/postgres/postgres.py
agno/db/postgres/schemas.py
agno/db/postgres/utils.py
agno/db/redis/__init__.py
agno-2.3.21.dist-info/licenses/LICENSE
agno-2.3.21.dist-info/METADATA
agno-2.3.21.dist-info/WHEEL
agno-2.3.21.dist-info/top_level.txt
agno-2.3.21.dist-info/RECORD
